How2jQianduanJiaocheng/README.md
How2jQianduanJiaocheng/__init__.py
How2jQianduanJiaocheng/__main__.py
How2jQianduanJiaocheng/file.epub
How2jQianduanJiaocheng/index.html
How2jQianduanJiaocheng/css/__init__.py
How2jQianduanJiaocheng/css/annotations.css
How2jQianduanJiaocheng/css/main.css
How2jQianduanJiaocheng/css/normalize.css
How2jQianduanJiaocheng/css/popup.css
How2jQianduanJiaocheng/font/__init__.py
How2jQianduanJiaocheng/font/fontello.eot
How2jQianduanJiaocheng/font/fontello.svg
How2jQianduanJiaocheng/font/fontello.ttf
How2jQianduanJiaocheng/font/fontello.woff
How2jQianduanJiaocheng/img/__init__.py
How2jQianduanJiaocheng/img/annotator-glyph-sprite.png
How2jQianduanJiaocheng/img/annotator-icon-sprite.png
How2jQianduanJiaocheng/img/apple-touch-icon.png
How2jQianduanJiaocheng/img/cancelfullscreen.png
How2jQianduanJiaocheng/img/close.png
How2jQianduanJiaocheng/img/fullscreen.png
How2jQianduanJiaocheng/img/loader.gif
How2jQianduanJiaocheng/img/menu-icon.png
How2jQianduanJiaocheng/img/save.png
How2jQianduanJiaocheng/img/saved.png
How2jQianduanJiaocheng/img/settings-s.png
How2jQianduanJiaocheng/img/settings.png
How2jQianduanJiaocheng/img/star.png
How2jQianduanJiaocheng/js/__init__.py
How2jQianduanJiaocheng/js/epub.js
How2jQianduanJiaocheng/js/epub.min.js
How2jQianduanJiaocheng/js/epub.min.map
How2jQianduanJiaocheng/js/hooks.min.js
How2jQianduanJiaocheng/js/hooks.min.map
How2jQianduanJiaocheng/js/reader.js
How2jQianduanJiaocheng/js/reader.js.map
How2jQianduanJiaocheng/js/reader.min.js
How2jQianduanJiaocheng/js/reader.min.map
How2jQianduanJiaocheng/js/hooks/__init__.py
How2jQianduanJiaocheng/js/hooks/extensions/__init__.py
How2jQianduanJiaocheng/js/hooks/extensions/highlight.js
How2jQianduanJiaocheng/js/libs/__init__.py
How2jQianduanJiaocheng/js/libs/jquery.min.js
How2jQianduanJiaocheng/js/libs/localforage.min.js
How2jQianduanJiaocheng/js/libs/screenfull.js
How2jQianduanJiaocheng/js/libs/screenfull.min.js
How2jQianduanJiaocheng/js/libs/zip.min.js
how2j_qianduan_jiaocheng-2024.3.6.0.dist-info/METADATA
how2j_qianduan_jiaocheng-2024.3.6.0.dist-info/WHEEL
how2j_qianduan_jiaocheng-2024.3.6.0.dist-info/entry_points.txt
how2j_qianduan_jiaocheng-2024.3.6.0.dist-info/top_level.txt
how2j_qianduan_jiaocheng-2024.3.6.0.dist-info/RECORD
